[
  {
    "Valide": 1,
    "Carrière": "Abbateur",
    "Type": "Artisanat",
    "Guilde": "collège des commerçants",
    "Filière": "maistre",
    "Profit": "2d3",
    "Métier 1": "Écorcheur",
    "Compétence 1": "dépeçage",
    "Bonus 1": "+1 DEX",
    "Métier 2": "Boucher",
    "Compétence 2": "découpe",
    "Bonus 2": "+1 FOR",
    "Métier 3": "Charcutier",
    "Compétence 3": "cuisine",
    "Bonus 3": "+1 SOC",
    "Métier 4": "Abbateur",
    "Compétence 4": "estimation",
    "Bonus 4": "+1 INS",
    "Danger": "",
    "Magie": "",
    "Quête": ""
  },
  {
    "Valide": 1,
    "Carrière": "Aigrefin",
    "Type": "Récolte",
    "Guilde": "guilde des Ombres",
    "Filière": "explorateur",
    "Profit": "1d12",
    "Métier 1": "Larron",
    "Compétence 1": "estimation",
    "Bonus 1": "+1 ERU",
    "Métier 2": "Larcineur",
    "Compétence 2": "rapine",
    "Bonus 2": "+1 MOU",
    "Métier 3": "Cambrioleur",
    "Compétence 3": "crochetage",
    "Bonus 3": "+1 DEX",
    "Métier 4": "Aigrefin",
    "Compétence 4": "escamotage",
    "Bonus 4": "+1 CHA",
    "Danger": 2,
    "Magie": "",
    "Quête": ""
  },
  {
    "Valide": 1,
    "Carrière": "Alchimiste",
    "Type": "Artisanat",
    "Guilde": "ordre des Médecins",
    "Filière": "maistre; courtisan",
    "Profit": "2d6",
    "Métier 1": "Laborantin",
    "Compétence 1": "planification",
    "Bonus 1": "+1 ERU",
    "Métier 2": "Chimiste",
    "Compétence 2": "chimie",
    "Bonus 2": "+1 DEX",
    "Métier 3": "Raffineur",
    "Compétence 3": "distillation",
    "Bonus 3": "+1 ERU",
    "Métier 4": "Alchimiste",
    "Compétence 4": "potions",
    "Bonus 4": "+1 INS",
    "Danger": "",
    "Magie": "",
    "Quête": ""
  },
  {
    "Valide": 1,
    "Carrière": "Ambassadeur",
    "Type": "Arts & Lettres",
    "Guilde": "les nasses",
    "Filière": "courtisan; politicien",
    "Profit": "1d6+4",
    "Métier 1": "Bonisseur",
    "Compétence 1": "course",
    "Bonus 1": "+1 SOC",
    "Métier 2": "Héraut",
    "Compétence 2": "récitation",
    "Bonus 2": "+1 ERU",
    "Métier 3": "Émissaire",
    "Compétence 3": "étiquette",
    "Bonus 3": "+1 SOC",
    "Métier 4": "Ambassadeur",
    "Compétence 4": "flagornerie",
    "Bonus 4": "+1 CHA",
    "Danger": "",
    "Magie": "",
    "Quête": ""
  },
  {
    "Valide": 1,
    "Carrière": "Apothicaire",
    "Type": "Artisanat",
    "Guilde": "guilde des forestiers",
    "Filière": "maistre",
    "Profit": "2d4+1",
    "Métier 1": "Cueilleur",
    "Compétence 1": "botanique",
    "Bonus 1": "+1 ERU",
    "Métier 2": "Botaniste",
    "Compétence 2": "premiers soins",
    "Bonus 2": "+1 DEX",
    "Métier 3": "Herboriste",
    "Compétence 3": "onguents",
    "Bonus 3": "+1 END",
    "Métier 4": "Apothicaire",
    "Compétence 4": "drogues",
    "Bonus 4": "+1 ERU",
    "Danger": "",
    "Magie": "",
    "Quête": ""
  },
  {
    "Valide": 0,
    "Carrière": "Apôtre",
    "Type": "Spirituel",
    "Guilde": "patron",
    "Filière": "courtisan; guide",
    "Profit": "",
    "Métier 1": "Pactiseur",
    "Compétence 1": "vents magiques",
    "Bonus 1": "+1 VIE",
    "Métier 2": "Fidèle",
    "Compétence 2": "comédie",
    "Bonus 2": "+2/-1",
    "Métier 3": "Laquais",
    "Compétence 3": "pantomime",
    "Bonus 3": "+3/-2",
    "Métier 4": "Apôtre",
    "Compétence 4": "séduction",
    "Bonus 4": "+4/-3",
    "Danger": "",
    "Magie": "",
    "Quête": ""
  },
  {
    "Valide": 1,
    "Carrière": "Arpenteur",
    "Type": "Artisanat",
    "Guilde": "guilde des artisans",
    "Filière": "maistre",
    "Profit": "1d6",
    "Métier 1": "Mineur",
    "Compétence 1": "activité minière",
    "Bonus 1": "+1 FOR",
    "Métier 2": "Sondeur",
    "Compétence 2": "géologie",
    "Bonus 2": "+1 ERU",
    "Métier 3": "Contremaître",
    "Compétence 3": "cartographie",
    "Bonus 3": "+1 INS",
    "Métier 4": "Arpenteur",
    "Compétence 4": "géométrie",
    "Bonus 4": "+1 ERU",
    "Danger": "",
    "Magie": "",
    "Quête": ""
  },
  {
    "Valide": 1,
    "Carrière": "Assassin",
    "Type": "Service",
    "Guilde": "guilde des ombres",
    "Filière": "vétéran; explorateur; guide",
    "Profit": "4d3",
    "Métier 1": "Éclaireur",
    "Compétence 1": "sournoiserie",
    "Bonus 1": "+1 MOU",
    "Métier 2": "Espion",
    "Compétence 2": "comédie",
    "Bonus 2": "+1 SOC",
    "Métier 3": "Spadassin",
    "Compétence 3": "escalade",
    "Bonus 3": "+1 AGI",
    "Métier 4": "Assassin",
    "Compétence 4": "camouflage",
    "Bonus 4": "+1 DEX",
    "Danger": 2,
    "Magie": "",
    "Quête": ""
  },
  {
    "Valide": 1,
    "Carrière": "Baleinier",
    "Type": "Récolte",
    "Guilde": "collège des commerçants",
    "Filière": "explorateur",
    "Profit": "1d6",
    "Métier 1": "Brayeur",
    "Compétence 1": "pièges",
    "Bonus 1": "+1 AGI",
    "Métier 2": "Pêcheur",
    "Compétence 2": "pêche",
    "Bonus 2": "+1 INS",
    "Métier 3": "Chasse-marée",
    "Compétence 3": "nœuds",
    "Bonus 3": "+1 FOR",
    "Métier 4": "Baleinier",
    "Compétence 4": "navigation",
    "Bonus 4": "+1 COU",
    "Danger": 1,
    "Magie": "",
    "Quête": ""
  },
  {
    "Valide": 1,
    "Carrière": "Bandit",
    "Type": "Récolte",
    "Guilde": "guilde des ombres",
    "Filière": "vétéran; politicien",
    "Profit": "1d6",
    "Métier 1": "Pillard",
    "Compétence 1": "fouilles",
    "Bonus 1": "+1 MOU",
    "Métier 2": "Coupe-jarret",
    "Compétence 2": "comédie",
    "Bonus 2": "+1 CHA",
    "Métier 3": "Brigand",
    "Compétence 3": "camouflage",
    "Bonus 3": "+1 ERU",
    "Métier 4": "Bandit",
    "Compétence 4": "duperie",
    "Bonus 4": "+1 CHA",
    "Danger": 2,
    "Magie": "",
    "Quête": ""
  },
  {
    "Valide": 1,
    "Carrière": "Barde",
    "Type": "Arts & Lettres",
    "Guilde": "forum des arts",
    "Filière": "courtisan; explorateur",
    "Profit": "1d6",
    "Métier 1": "Colporteur",
    "Compétence 1": "commérage",
    "Bonus 1": "+1 SOC",
    "Métier 2": "Conteur",
    "Compétence 2": "contes",
    "Bonus 2": "+1 SOC",
    "Métier 3": "Troubadour",
    "Compétence 3": "chant",
    "Bonus 3": "+1 ERU",
    "Métier 4": "Barde",
    "Compétence 4": "séduction",
    "Bonus 4": "+1 CHA",
    "Danger": "",
    "Magie": "",
    "Quête": ""
  },
  {
    "Valide": 1,
    "Carrière": "Chaman",
    "Type": "Spirituel",
    "Guilde": "guilde des forestiers",
    "Filière": "guide",
    "Profit": "1d4",
    "Métier 1": "Charmeur",
    "Compétence 1": "prestidigitation",
    "Bonus 1": "+1 SOC",
    "Métier 2": "Marabout",
    "Compétence 2": "rafistolage",
    "Bonus 2": "+1 DEX",
    "Métier 3": "Féticheur",
    "Compétence 3": "potions",
    "Bonus 3": "+1 ÉRU",
    "Métier 4": "Chaman",
    "Compétence 4": "hypnose",
    "Bonus 4": "+1 SEN",
    "Danger": "",
    "Magie": 1,
    "Quête": ""
  },
  {
    "Valide": 1,
    "Carrière": "Charpentier",
    "Type": "Artisanat",
    "Guilde": "guilde des artisans",
    "Filière": "maistre",
    "Profit": "2d4",
    "Métier 1": "Bûcheron",
    "Compétence 1": "orientation",
    "Bonus 1": "+1 FOR",
    "Métier 2": "Escrignier",
    "Compétence 2": "sculpture",
    "Bonus 2": "+1 DEX",
    "Métier 3": "Menuisier",
    "Compétence 3": "menuiserie",
    "Bonus 3": "+1 FOR",
    "Métier 4": "Charpentier",
    "Compétence 4": "planification",
    "Bonus 4": "+1 ERU",
    "Danger": "",
    "Magie": "",
    "Quête": ""
  },
  {
    "Valide": 1,
    "Carrière": "Chasseur de trésor",
    "Type": "Récolte",
    "Guilde": "guilde des mendiants",
    "Filière": "vétéran; explorateur; guide",
    "Profit": "2d10",
    "Métier 1": "Exhumeur",
    "Compétence 1": "veille",
    "Bonus 1": "+1 COU",
    "Métier 2": "Charognard",
    "Compétence 2": "fouille",
    "Bonus 2": "+1 DEX",
    "Métier 3": "Naufrageur",
    "Compétence 3": "sabotage",
    "Bonus 3": "+1 AGI",
    "Métier 4": "Chasseur de trésor",
    "Compétence 4": "histoire & légendes",
    "Bonus 4": "+1 INS",
    "Danger": 1,
    "Magie": "",
    "Quête": ""
  },
  {
    "Valide": 1,
    "Carrière": "Chevalier",
    "Type": "Service",
    "Guilde": "église de la foi moufflienne",
    "Filière": "maistre; politicien; vétéran",
    "Profit": "3d3",
    "Métier 1": "Page",
    "Compétence 1": "soin des animaux",
    "Bonus 1": "+1 INS",
    "Métier 2": "Écuyer",
    "Compétence 2": "héraldique",
    "Bonus 2": "+1 ERU",
    "Métier 3": "Damoiseau",
    "Compétence 3": "séduction",
    "Bonus 3": "+1 CHA",
    "Métier 4": "Chevalier",
    "Compétence 4": "étiquette",
    "Bonus 4": "+1 SOC",
    "Danger": "",
    "Magie": "",
    "Quête": ""
  },
  {
    "Valide": 1,
    "Carrière": "Chirurgien",
    "Type": "Service",
    "Guilde": "ordre des Médecins",
    "Filière": "maistre",
    "Profit": "3d3",
    "Métier 1": "Secouriste",
    "Compétence 1": "premiers soins",
    "Bonus 1": "+1 COU",
    "Métier 2": "Interne",
    "Compétence 2": "veille",
    "Bonus 2": "+1 END",
    "Métier 3": "Médecin",
    "Compétence 3": "médecine",
    "Bonus 3": "+1 ERU",
    "Métier 4": "Chirurgien",
    "Compétence 4": "chirurgie",
    "Bonus 4": "+1 DEX",
    "Danger": "",
    "Magie": "",
    "Quête": ""
  },
  {
    "Valide": 1,
    "Carrière": "Collectionneur",
    "Type": "Récolte",
    "Guilde": "guilde des mendiants",
    "Filière": "explorateur",
    "Profit": "1d8 / 0",
    "Métier 1": "Décrotteur",
    "Compétence 1": "pistage",
    "Bonus 1": "+1 INS",
    "Métier 2": "Eboueur",
    "Compétence 2": "orientation",
    "Bonus 2": "+1 FOR",
    "Métier 3": "Brocanteur",
    "Compétence 3": "estimation",
    "Bonus 3": "+1 SOC",
    "Métier 4": "Collectionneur",
    "Compétence 4": "histoire & légendes",
    "Bonus 4": "+1 ERU",
    "Danger": "",
    "Magie": "",
    "Quête": ""
  },
  {
    "Valide": 1,
    "Carrière": "Comédien",
    "Type": "Arts & Lettres",
    "Guilde": "forum des arts",
    "Filière": "courtisan; politicien",
    "Profit": "1d4",
    "Métier 1": "Bateleur",
    "Compétence 1": "humour",
    "Bonus 1": "+1 SOC",
    "Métier 2": "Cabotin",
    "Compétence 2": "chant",
    "Bonus 2": "+1 CHA",
    "Métier 3": "Saltimbanque",
    "Compétence 3": "danse",
    "Bonus 3": "+1 AGI",
    "Métier 4": "Comédien",
    "Compétence 4": "récitation",
    "Bonus 4": "+1 CHA",
    "Danger": "",
    "Magie": "",
    "Quête": ""
  },
  {
    "Valide": 1,
    "Carrière": "Conférencier",
    "Type": "Arts & Lettres",
    "Guilde": "les nasses",
    "Filière": "maistre; politicien",
    "Profit": "1d4+1",
    "Métier 1": "Estudiant",
    "Compétence 1": "lecture & écriture",
    "Bonus 1": "+1 ERU",
    "Métier 2": "Chercheur",
    "Compétence 2": "veille",
    "Bonus 2": "+1 ERU",
    "Métier 3": "Professeur",
    "Compétence 3": "enseignement",
    "Bonus 3": "+1 SOC",
    "Métier 4": "Conférencier",
    "Compétence 4": "éloquence",
    "Bonus 4": "+1 CHA",
    "Danger": "",
    "Magie": "",
    "Quête": ""
  },
  {
    "Valide": 1,
    "Carrière": "Contrebandier",
    "Type": "Récolte",
    "Guilde": "guilde des Ombres",
    "Filière": "explorateur",
    "Profit": "2d6",
    "Métier 1": "Escroc",
    "Compétence 1": "baratin",
    "Bonus 1": "+1 SOC",
    "Métier 2": "Fraudeur",
    "Compétence 2": "législation",
    "Bonus 2": "+1 ERU",
    "Métier 3": "Faussaire",
    "Compétence 3": "réplique",
    "Bonus 3": "+1 DEX",
    "Métier 4": "Contrebandier",
    "Compétence 4": "commerce",
    "Bonus 4": "+1 CHA",
    "Danger": 2,
    "Magie": "",
    "Quête": ""
  },
  {
    "Valide": 1,
    "Carrière": "Détective",
    "Type": "Service",
    "Guilde": "conciergerie",
    "Filière": "vétéran; politicien",
    "Profit": "1d4+1",
    "Métier 1": "Recrue",
    "Compétence 1": "législation",
    "Bonus 1": "+1 ERU",
    "Métier 2": "Limier",
    "Compétence 2": "commérage",
    "Bonus 2": "+1 SOC",
    "Métier 3": "Enquêteur",
    "Compétence 3": "filature",
    "Bonus 3": "+1 ERU",
    "Métier 4": "Détective",
    "Compétence 4": "sincérité",
    "Bonus 4": "+1 INS",
    "Danger": "",
    "Magie": "",
    "Quête": ""
  },
  {
    "Valide": 1,
    "Carrière": "Druide",
    "Type": "Spirituel",
    "Guilde": "guilde des forestiers",
    "Filière": "explorateur; guide",
    "Profit": "1d3",
    "Métier 1": "Voyant",
    "Compétence 1": "astrologie",
    "Bonus 1": "+1 INS",
    "Métier 2": "Devin",
    "Compétence 2": "divination",
    "Bonus 2": "+1 SEN",
    "Métier 3": "Ovate",
    "Compétence 3": "soin des animaux",
    "Bonus 3": "+1 INS",
    "Métier 4": "Druide",
    "Compétence 4": "méditation",
    "Bonus 4": "+1 SEN",
    "Danger": "",
    "Magie": 1,
    "Quête": ""
  },
  {
    "Valide": 1,
    "Carrière": "Duelliste",
    "Type": "Service",
    "Guilde": "guilde des Ombres",
    "Filière": "vétéran; courtisan",
    "Profit": "2d4",
    "Métier 1": "Parieur",
    "Compétence 1": "bras de fer",
    "Bonus 1": "+1 FOR",
    "Métier 2": "Pugiliste",
    "Compétence 2": "assommage",
    "Bonus 2": "+1 END",
    "Métier 3": "Jouteur",
    "Compétence 3": "esquive",
    "Bonus 3": "+1 AGI",
    "Métier 4": "Duelliste",
    "Compétence 4": "désarmement",
    "Bonus 4": "+1 CHA",
    "Danger": 1,
    "Magie": "",
    "Quête": ""
  },
  {
    "Valide": 1,
    "Carrière": "Embaumeur",
    "Type": "Service",
    "Guilde": "collège des commerçants",
    "Filière": "courtisan; maistre",
    "Profit": "2d3",
    "Métier 1": "Fossoyeur",
    "Compétence 1": "activité minière",
    "Bonus 1": "+1 COU",
    "Métier 2": "Juré-crieur",
    "Compétence 2": "orientation",
    "Bonus 2": "+1 SOC",
    "Métier 3": "Croquemort",
    "Compétence 3": "conserves",
    "Bonus 3": "+1 COU",
    "Métier 4": "Embaumeur",
    "Compétence 4": "remèdes",
    "Bonus 4": "+1 DEX",
    "Danger": "",
    "Magie": "",
    "Quête": ""
  },
  {
    "Valide": 1,
    "Carrière": "Enchanteur",
    "Type": "Spirituel",
    "Guilde": "confrérie des Loups-Gris",
    "Filière": "courtisan; maistre; guide",
    "Profit": "2d6",
    "Métier 1": "Prestidigitateur",
    "Compétence 1": "pantomime",
    "Bonus 1": "+1 CHA",
    "Métier 2": "Illusioniste",
    "Compétence 2": "incantation",
    "Bonus 2": "+1 SEN",
    "Métier 3": "Magicien",
    "Compétence 3": "magidentification",
    "Bonus 3": "+1 SEN",
    "Métier 4": "Enchanteur",
    "Compétence 4": "enchantement",
    "Bonus 4": "+1 ERU",
    "Danger": "",
    "Magie": 1,
    "Quête": ""
  },
  {
    "Valide": 1,
    "Carrière": "Enlumineur",
    "Type": "Artisanat",
    "Guilde": "guilde des artisans",
    "Filière": "maistre",
    "Profit": "1d4+1",
    "Métier 1": "Copiste",
    "Compétence 1": "lecture & écriture",
    "Bonus 1": "+1 DEX",
    "Métier 2": "Scribe",
    "Compétence 2": "classement",
    "Bonus 2": "+1 ERU",
    "Métier 3": "Parcheminier",
    "Compétence 3": "tannage",
    "Bonus 3": "+1 END",
    "Métier 4": "Enlumineur",
    "Compétence 4": "dessin",
    "Bonus 4": "+1 DEX",
    "Danger": "",
    "Magie": "",
    "Quête": ""
  },
  {
    "Valide": 1,
    "Carrière": "Ensorceleur",
    "Type": "Spirituel",
    "Guilde": "guilde des ombres",
    "Filière": "courtisan; guide",
    "Profit": "2d4",
    "Métier 1": "Mystique",
    "Compétence 1": "chiromancie",
    "Bonus 1": "+1 CHA",
    "Métier 2": "Spirite",
    "Compétence 2": "spiritisme",
    "Bonus 2": "+1 ERU",
    "Métier 3": "Sorcier",
    "Compétence 3": "incantation",
    "Bonus 3": "+1 SEN",
    "Métier 4": "Ensorceleur",
    "Compétence 4": "glyphes",
    "Bonus 4": "+1 ERU",
    "Danger": "",
    "Magie": 1,
    "Quête": ""
  },
  {
    "Valide": 1,
    "Carrière": "Entremetteur",
    "Type": "Récolte",
    "Guilde": "collège des commerçants",
    "Filière": "explorateur; courtisan",
    "Profit": "3d4",
    "Métier 1": "Extorqueur",
    "Compétence 1": "intimidation",
    "Bonus 1": "+1 CHA",
    "Métier 2": "Ravisseur",
    "Compétence 2": "crochetage",
    "Bonus 2": "+1 FOR",
    "Métier 3": "Esclavagiste",
    "Compétence 3": "commerce",
    "Bonus 3": "+1 SOC",
    "Métier 4": "Entremetteur",
    "Compétence 4": "étiquette",
    "Bonus 4": "+1 CHA",
    "Danger": 2,
    "Magie": "",
    "Quête": ""
  },
  {
    "Valide": 1,
    "Carrière": "Evêque",
    "Type": "Spirituel",
    "Guilde": "église de la foi moufflienne",
    "Filière": "courtisan; maistre; guide",
    "Profit": "3d4",
    "Métier 1": "Page",
    "Compétence 1": "religion & cultes",
    "Bonus 1": "+1 SEN",
    "Métier 2": "Copiste",
    "Compétence 2": "lecture & écriture",
    "Bonus 2": "+1 DEX",
    "Métier 3": "Prêtre",
    "Compétence 3": "éloquence",
    "Bonus 3": "+1 SOC",
    "Métier 4": "Evêque",
    "Compétence 4": "politesse",
    "Bonus 4": "+1 CHA",
    "Danger": "",
    "Magie": "",
    "Quête": ""
  },
  {
    "Valide": 1,
    "Carrière": "Ferronnier",
    "Type": "Artisanat",
    "Guilde": "guilde des artisans",
    "Filière": "maistre",
    "Profit": "1d10",
    "Métier 1": "Rémouleur",
    "Compétence 1": "réparation",
    "Bonus 1": "+1 END",
    "Métier 2": "Chaudronnier",
    "Compétence 2": "feu",
    "Bonus 2": "+1 END",
    "Métier 3": "Forgeron",
    "Compétence 3": "forge",
    "Bonus 3": "+1 FOR",
    "Métier 4": "Ferronnier",
    "Compétence 4": "mécanique",
    "Bonus 4": "+1 ERU",
    "Danger": "",
    "Magie": "",
    "Quête": ""
  },
  {
    "Valide": 1,
    "Carrière": "Gourou",
    "Type": "Spirituel",
    "Guilde": "collège des commerçants",
    "Filière": "courtisan; guide",
    "Profit": "4d4",
    "Métier 1": "Disciple",
    "Compétence 1": "baratin",
    "Bonus 1": "+1 COU",
    "Métier 2": "Prêcheur",
    "Compétence 2": "persuasion",
    "Bonus 2": "+1 SOC",
    "Métier 3": "Cultiste",
    "Compétence 3": "récitation",
    "Bonus 3": "+1 END",
    "Métier 4": "Gourou",
    "Compétence 4": "éloquence",
    "Bonus 4": "+1 CHA",
    "Danger": "",
    "Magie": "",
    "Quête": ""
  },
  {
    "Valide": 1,
    "Carrière": "Grand Joueur",
    "Type": "Récolte",
    "Guilde": "collège des commerçants",
    "Filière": "courtisan; guide",
    "Profit": "± 1D8",
    "Métier 1": "Arnaqueur",
    "Compétence 1": "baratin",
    "Bonus 1": "+1 SOC",
    "Métier 2": "Compétiteur",
    "Compétence 2": "duperie",
    "Bonus 2": "+1 INS",
    "Métier 3": "Croupier",
    "Compétence 3": "jeux",
    "Bonus 3": "+1 DEX",
    "Métier 4": "Grand Joueur",
    "Compétence 4": "sincérité",
    "Bonus 4": "+1 ERU",
    "Danger": "",
    "Magie": "",
    "Quête": ""
  },
  {
    "Valide": 1,
    "Carrière": "Importateur",
    "Type": "Service",
    "Guilde": "collège des commerçants",
    "Filière": "courtisan; maistre; explorateur",
    "Profit": "1d4+3",
    "Métier 1": "Vaurien",
    "Compétence 1": "escamotage",
    "Bonus 1": "+1 INS",
    "Métier 2": "Receleur",
    "Compétence 2": "estimation",
    "Bonus 2": "+1 ERU",
    "Métier 3": "Trafiquant",
    "Compétence 3": "drogues",
    "Bonus 3": "+1 SOC",
    "Métier 4": "Importateur",
    "Compétence 4": "commerce",
    "Bonus 4": "+1 CHA",
    "Danger": "",
    "Magie": "",
    "Quête": ""
  },
  {
    "Valide": 1,
    "Carrière": "Ingénieur",
    "Type": "Artisanat",
    "Guilde": "guilde des artisans",
    "Filière": "maistre",
    "Profit": "2d6+1",
    "Métier 1": "Réparateur",
    "Compétence 1": "réparation",
    "Bonus 1": "+1 DEX",
    "Métier 2": "Mécanicien",
    "Compétence 2": "technologie",
    "Bonus 2": "+1 ERU",
    "Métier 3": "Artificier",
    "Compétence 3": "explosifs",
    "Bonus 3": "+1 INS",
    "Métier 4": "Ingénieur",
    "Compétence 4": "dessin",
    "Bonus 4": "+1 ERU",
    "Danger": "",
    "Magie": "",
    "Quête": ""
  },
  {
    "Valide": 1,
    "Carrière": "Juge",
    "Type": "Arts & Lettres",
    "Guilde": "collège des commerçants",
    "Filière": "maistre; politicien",
    "Profit": "3d3",
    "Métier 1": "Greffier",
    "Compétence 1": "dactylographie",
    "Bonus 1": "+1 DEX",
    "Métier 2": "Juriste",
    "Compétence 2": "législation",
    "Bonus 2": "+1 ERU",
    "Métier 3": "Avocat",
    "Compétence 3": "persuasion",
    "Bonus 3": "+1 CHA",
    "Métier 4": "Juge",
    "Compétence 4": "éloquence",
    "Bonus 4": "+1 CHA",
    "Danger": "",
    "Magie": "",
    "Quête": ""
  },
  {
    "Valide": 1,
    "Carrière": "Maître-chanteur",
    "Type": "Récolte",
    "Guilde": "guilde des mendiants",
    "Filière": "courtisan; politicien",
    "Profit": "2d4",
    "Métier 1": "Mendiant",
    "Compétence 1": "mendicité",
    "Bonus 1": "+1 CHA",
    "Métier 2": "Fouineur",
    "Compétence 2": "commérage",
    "Bonus 2": "+1 SOC",
    "Métier 3": "Indicateur",
    "Compétence 3": "camouflage",
    "Bonus 3": "+1 INS",
    "Métier 4": "Maître-chanteur",
    "Compétence 4": "corruption",
    "Bonus 4": "+1 SOC",
    "Danger": "",
    "Magie": "",
    "Quête": ""
  },
  {
    "Valide": 1,
    "Carrière": "Maître-toque",
    "Type": "Artisanat",
    "Guilde": "guilde des artisans",
    "Filière": "maistre",
    "Profit": "2d3",
    "Métier 1": "Commis",
    "Compétence 1": "découpe",
    "Bonus 1": "+1 COU",
    "Métier 2": "Cantinier",
    "Compétence 2": "cuisine",
    "Bonus 2": "+1 SOC",
    "Métier 3": "Cuisinier",
    "Compétence 3": "jeûn",
    "Bonus 3": "+1 END",
    "Métier 4": "Maître-toque",
    "Compétence 4": "composition",
    "Bonus 4": "+1 CHA",
    "Danger": "",
    "Magie": "",
    "Quête": ""
  },
  {
    "Valide": 1,
    "Carrière": "Maroquinier",
    "Type": "Artisanat",
    "Guilde": "guilde des artisans",
    "Filière": "courtisan; maistre",
    "Profit": "2d6",
    "Métier 1": "Tanneur",
    "Compétence 1": "tannage",
    "Bonus 1": "+1 END",
    "Métier 2": "Relieur",
    "Compétence 2": "cordonnerie",
    "Bonus 2": "+1 DEX",
    "Métier 3": "Cordonnier",
    "Compétence 3": "réparation",
    "Bonus 3": "+1 SOC",
    "Métier 4": "Maroquinier",
    "Compétence 4": "confection",
    "Bonus 4": "+1 DEX",
    "Danger": "",
    "Magie": "",
    "Quête": ""
  },
  {
    "Valide": 1,
    "Carrière": "Milicien",
    "Type": "Service",
    "Guilde": "conciergerie",
    "Filière": "vétéran",
    "Profit": 3,
    "Métier 1": "Lanternier",
    "Compétence 1": "escalade",
    "Bonus 1": "+1 COU",
    "Métier 2": "Veilleur",
    "Compétence 2": "veille",
    "Bonus 2": "+1 INS",
    "Métier 3": "Garde",
    "Compétence 3": "intimidation",
    "Bonus 3": "+1 SOC",
    "Métier 4": "Milicien",
    "Compétence 4": "course",
    "Bonus 4": "+1 MOU",
    "Danger": 1,
    "Magie": "",
    "Quête": ""
  },
  {
    "Valide": 1,
    "Carrière": "Navigateur",
    "Type": "Service",
    "Guilde": "guilde du beurre",
    "Filière": "explorateur; vétéran",
    "Profit": "1d6",
    "Métier 1": "Batelier",
    "Compétence 1": "nage",
    "Bonus 1": "+1 FOR",
    "Métier 2": "Vigie",
    "Compétence 2": "équilibre",
    "Bonus 2": "+1 AGI",
    "Métier 3": "Timonier",
    "Compétence 3": "navigation",
    "Bonus 3": "+1 INS",
    "Métier 4": "Navigateur",
    "Compétence 4": "cartographie",
    "Bonus 4": "+1 INS",
    "Danger": 1,
    "Magie": "",
    "Quête": ""
  },
  {
    "Valide": 1,
    "Carrière": "Paladin",
    "Type": "Spirituel",
    "Guilde": "église de la foi moufflienne",
    "Filière": "explorateur, guide; vétéran",
    "Profit": "3d3",
    "Métier 1": "Pénitent",
    "Compétence 1": "jeûne",
    "Bonus 1": "+1 VIE",
    "Métier 2": "Pélerin",
    "Compétence 2": "orientation",
    "Bonus 2": "+1 END",
    "Métier 3": "Hospitalier",
    "Compétence 3": "masses",
    "Bonus 3": "+1 COU",
    "Métier 4": "Paladin",
    "Compétence 4": "vents magiques",
    "Bonus 4": "+1 SEN",
    "Danger": 1,
    "Magie": 1,
    "Quête": ""
  },
  {
    "Valide": 1,
    "Carrière": "Parfumeur",
    "Type": "Service",
    "Guilde": "guilde des artisans",
    "Filière": "courtisan; maistre",
    "Profit": "2d6",
    "Métier 1": "Savonnier",
    "Compétence 1": "botanique",
    "Bonus 1": "+1 ERU",
    "Métier 2": "Barbier",
    "Compétence 2": "coiffure",
    "Bonus 2": "+1 SOC",
    "Métier 3": "Maquilleur",
    "Compétence 3": "grimage",
    "Bonus 3": "+1 DEX",
    "Métier 4": "Parfumeur",
    "Compétence 4": "distillation",
    "Bonus 4": "+1 CHA",
    "Danger": "",
    "Magie": "",
    "Quête": ""
  },
  {
    "Valide": 1,
    "Carrière": "Passe-sentier",
    "Type": "Service",
    "Guilde": "guilde des forestiers",
    "Filière": "explorateur; vétéran",
    "Profit": "1d3",
    "Métier 1": "Forestier",
    "Compétence 1": "survie",
    "Bonus 1": "+1 END",
    "Métier 2": "Trappeur",
    "Compétence 2": "pièges",
    "Bonus 2": "+1 DEX",
    "Métier 3": "Pisteur",
    "Compétence 3": "pistage",
    "Bonus 3": "+1 MOU",
    "Métier 4": "Passe-sentier",
    "Compétence 4": "camouflage",
    "Bonus 4": "+1 INS",
    "Danger": "",
    "Magie": "",
    "Quête": ""
  },
  {
    "Valide": 1,
    "Carrière": "Philosophe",
    "Type": "Arts & Lettres",
    "Guilde": "les nasses",
    "Filière": "courtisan; guide; politicien",
    "Profit": "1d3",
    "Métier 1": "Poète",
    "Compétence 1": "rimes",
    "Bonus 1": "+1 SOC",
    "Métier 2": "Ecrivain",
    "Compétence 2": "lecture & écriture",
    "Bonus 2": "+1 DEX",
    "Métier 3": "Essayiste",
    "Compétence 3": "persuasion",
    "Bonus 3": "+1 ERU",
    "Métier 4": "Philosophe",
    "Compétence 4": "rhétorique",
    "Bonus 4": "+1 CHA",
    "Danger": "",
    "Magie": "",
    "Quête": ""
  },
  {
    "Valide": 0,
    "Carrière": "Régisseur",
    "Type": "Service",
    "Guilde": "guilde du Beurre",
    "Filière": "courtisan",
    "Profit": "",
    "Métier 1": "Coursier",
    "Compétence 1": "orientation",
    "Bonus 1": "+1 MOU",
    "Métier 2": "Servant",
    "Compétence 2": "déplacement silencieux",
    "Bonus 2": "+1 SOC",
    "Métier 3": "Régisseur",
    "Compétence 3": "étiquette",
    "Bonus 3": "+1 CHA",
    "Métier 4": "",
    "Compétence 4": "",
    "Bonus 4": "",
    "Danger": "",
    "Magie": "",
    "Quête": ""
  },
  {
    "Valide": 1,
    "Carrière": "Plaisant",
    "Type": "Arts & Lettres",
    "Guilde": "forum des arts",
    "Filière": "courtisan; politicien",
    "Profit": "-",
    "Métier 1": "Jongleur",
    "Compétence 1": "acrobatie",
    "Bonus 1": "+1 AGI",
    "Métier 2": "Marionnetiste",
    "Compétence 2": "imitation",
    "Bonus 2": "+1 DEX",
    "Métier 3": "Ménestrel",
    "Compétence 3": "étiquette",
    "Bonus 3": "+1 CHA",
    "Métier 4": "Plaisant",
    "Compétence 4": "jeux de mots",
    "Bonus 4": "+1 SOC",
    "Danger": "",
    "Magie": "",
    "Quête": ""
  },
  {
    "Valide": 1,
    "Carrière": "Protecteur",
    "Type": "Service",
    "Guilde": "guilde des ombres",
    "Filière": "vétéran",
    "Profit": "2d3+1",
    "Métier 1": "Videur",
    "Compétence 1": "intimidation",
    "Bonus 1": "+1 INS",
    "Métier 2": "Lutteur",
    "Compétence 2": "lutte",
    "Bonus 2": "+1 END",
    "Métier 3": "Combattant",
    "Compétence 3": "esquive",
    "Bonus 3": "+1 AGI",
    "Métier 4": "Protecteur",
    "Compétence 4": "étiquette",
    "Bonus 4": "+1 CHA",
    "Danger": 1,
    "Magie": "",
    "Quête": ""
  },
  {
    "Valide": 1,
    "Carrière": "Répurgateur",
    "Type": "Spirituel",
    "Guilde": "église de la foi moufflienne",
    "Filière": "courtisan; guide",
    "Profit": "2d4",
    "Métier 1": "Clerc",
    "Compétence 1": "lecture & écriture",
    "Bonus 1": "+1 ERU",
    "Métier 2": "Occultiste",
    "Compétence 2": "vents magiques",
    "Bonus 2": "+1 SEN",
    "Métier 3": "Exorciste",
    "Compétence 3": "spiritisme",
    "Bonus 3": "+1 COU",
    "Métier 4": "Répurgateur",
    "Compétence 4": "enquête",
    "Bonus 4": "+1 COU",
    "Danger": 1,
    "Magie": 1,
    "Quête": ""
  },
  {
    "Valide": 1,
    "Carrière": "Sculpteur",
    "Type": "Artisanat",
    "Guilde": "guilde des artisans",
    "Filière": "courtisan; maistre",
    "Profit": "2d3",
    "Métier 1": "Carrier",
    "Compétence 1": "masses",
    "Bonus 1": "+1 FOR",
    "Métier 2": "Tailleur de pierre",
    "Compétence 2": "géologie",
    "Bonus 2": "+1 ERU",
    "Métier 3": "Graveur",
    "Compétence 3": "sculpture",
    "Bonus 3": "+1 DEX",
    "Métier 4": "Sculpteur",
    "Compétence 4": "composition",
    "Bonus 4": "+1 ERU",
    "Danger": "",
    "Magie": "",
    "Quête": ""
  },
  {
    "Valide": 0,
    "Carrière": "Taxidermiste",
    "Type": "Artisanat",
    "Guilde": "guilde des artisans",
    "Filière": "maester",
    "Profit": "",
    "Métier 1": "Braconnier",
    "Compétence 1": "pièges",
    "Bonus 1": "+1 DEX",
    "Métier 2": "Trappeur",
    "Compétence 2": "pistage",
    "Bonus 2": "+1 INS",
    "Métier 3": "Taxidermiste",
    "Compétence 3": "empaillage",
    "Bonus 3": "-1 SOC",
    "Métier 4": "",
    "Compétence 4": "",
    "Bonus 4": "",
    "Danger": "",
    "Magie": "",
    "Quête": ""
  },
  {
    "Valide": 0,
    "Carrière": "Trafiquant",
    "Type": "Service",
    "Guilde": "guilde des commerçants",
    "Filière": "courtisan; politicien",
    "Profit": "",
    "Métier 1": "Chouffeur",
    "Compétence 1": "sifflage",
    "Bonus 1": "+1 INS",
    "Métier 2": "Charbonneur",
    "Compétence 2": "calcul mental",
    "Bonus 2": "+1 INS",
    "Métier 3": "Coupeur",
    "Compétence 3": "commerce",
    "Bonus 3": "-1 END",
    "Métier 4": "Trafiquant",
    "Compétence 4": "sincérité",
    "Bonus 4": "-1 SOC",
    "Danger": "",
    "Magie": "",
    "Quête": ""
  },
  {
    "Valide": 1,
    "Carrière": "Sénéchal",
    "Type": "Arts & Lettres",
    "Guilde": "les nasses",
    "Filière": "courtisan; politicien",
    "Profit": "3d3+1",
    "Métier 1": "Comptable",
    "Compétence 1": "calcul mental",
    "Bonus 1": "+1 ERU",
    "Métier 2": "Intendant",
    "Compétence 2": "intimidation",
    "Bonus 2": "+1 SOC",
    "Métier 3": "Trésorier",
    "Compétence 3": "classement",
    "Bonus 3": "+1 ERU",
    "Métier 4": "Sénéchal",
    "Compétence 4": "commandement",
    "Bonus 4": "+1 CHA",
    "Danger": "",
    "Magie": "",
    "Quête": ""
  },
  {
    "Valide": 1,
    "Carrière": "Tailleur",
    "Type": "Artisanat",
    "Guilde": "guilde des artisans",
    "Filière": "courtisan; maistre",
    "Profit": "2d6",
    "Métier 1": "Dévideur",
    "Compétence 1": "rafistolage",
    "Bonus 1": "+1 DEX",
    "Métier 2": "Repriseur",
    "Compétence 2": "textiles",
    "Bonus 2": "+1 SOC",
    "Métier 3": "Couturier",
    "Compétence 3": "héraldique",
    "Bonus 3": "+1 ERU",
    "Métier 4": "Tailleur",
    "Compétence 4": "étiquette",
    "Bonus 4": "+1 SOC",
    "Danger": "",
    "Magie": "",
    "Quête": ""
  },
  {
    "Valide": 1,
    "Carrière": "Thaumaturge",
    "Type": "Spirituel",
    "Guilde": "guilde des forestiers",
    "Filière": "maistre; courtisan; explorateur",
    "Profit": "1d6",
    "Métier 1": "Rebouteur",
    "Compétence 1": "simples",
    "Bonus 1": "+1 INS",
    "Métier 2": "Guérisseur",
    "Compétence 2": "premiers soins",
    "Bonus 2": "+1 ERU",
    "Métier 3": "Ascète",
    "Compétence 3": "méditation",
    "Bonus 3": "+1 SEN",
    "Métier 4": "Thaumaturge",
    "Compétence 4": "vents magiques",
    "Bonus 4": "+1 CHA",
    "Danger": "",
    "Magie": 1,
    "Quête": ""
  },
  {
    "Valide": 1,
    "Carrière": "Tueur",
    "Type": "Service",
    "Guilde": "guilde des forestiers",
    "Filière": "vétéran; explorateur",
    "Profit": "2d4",
    "Métier 1": "Chasseur",
    "Compétence 1": "dépeçage",
    "Bonus 1": "+1 INS",
    "Métier 2": "Égoutier",
    "Compétence 2": "orientation",
    "Bonus 2": "+1 COU",
    "Métier 3": "Éradicateur",
    "Compétence 3": "poisons",
    "Bonus 3": "+1 END",
    "Métier 4": "Tueur",
    "Compétence 4": "pistage",
    "Bonus 4": "+1 COU",
    "Danger": 1,
    "Magie": "",
    "Quête": ""
  },
  {
    "Valide": 1,
    "Carrière": "Voiturier",
    "Type": "Service",
    "Guilde": "guilde du beurre",
    "Filière": "courtisan; explorateur",
    "Profit": "1d4",
    "Métier 1": "Palefrenier",
    "Compétence 1": "soin des animaux",
    "Bonus 1": "+1 INS",
    "Métier 2": "Relayeur",
    "Compétence 2": "équitation",
    "Bonus 2": "+1 END",
    "Métier 3": "Cocher",
    "Compétence 3": "conduite",
    "Bonus 3": "+1 INS",
    "Métier 4": "Voiturier",
    "Compétence 4": "politesse",
    "Bonus 4": "+1 SOC",
    "Danger": "",
    "Magie": "",
    "Quête": ""
  },
  {
    "Valide": 1,
    "Carrière": "Corsaire",
    "Type": "Récolte",
    "Guilde": "collège des commerçants",
    "Filière": "explorateur; vétéran",
    "Profit": "2d3",
    "Métier 1": "Mousse",
    "Compétence 1": "nœuds",
    "Bonus 1": "+1 DEX",
    "Métier 2": "Gabier",
    "Compétence 2": "acrobatie",
    "Bonus 2": "+1 AGI",
    "Métier 3": "Flibustier",
    "Compétence 3": "intimidation",
    "Bonus 3": "+1 COU",
    "Métier 4": "Corsaire",
    "Compétence 4": "commerce",
    "Bonus 4": "+1 CHA",
    "Danger": 1,
    "Magie": "",
    "Quête": ""
  },
  {
    "Valide": 1,
    "Carrière": "Éleveur",
    "Type": "Artisanat",
    "Guilde": "guilde des artisans",
    "Filière": "maistre, courtisan",
    "Profit": "2d4",
    "Métier 1": "Soigneur",
    "Compétence 1": "soin des animaux",
    "Bonus 1": "+1 ERU",
    "Métier 2": "Sélectionneur",
    "Compétence 2": "classement",
    "Bonus 2": "+1 INS",
    "Métier 3": "Dompteur",
    "Compétence 3": "dressage",
    "Bonus 3": "+1 INS",
    "Métier 4": "Éleveur",
    "Compétence 4": "commerce",
    "Bonus 4": "+1 CHA",
    "Danger": "",
    "Magie": "",
    "Quête": ""
  },
  {
    "Valide": 1,
    "Carrière": "Archimage",
    "Type": "Spirituel",
    "Guilde": "guilde des forestiers",
    "Filière": "maistre, explorateur",
    "Profit": "2d6",
    "Métier 1": "Ésotériste",
    "Compétence 1": "cartomancie",
    "Bonus 1": "+1 SEN",
    "Métier 2": "Cabaliste",
    "Compétence 2": "potions",
    "Bonus 2": "+1 DEX",
    "Métier 3": "Arcaniste",
    "Compétence 3": "pantomime",
    "Bonus 3": "+1 ERU",
    "Métier 4": "Archimage",
    "Compétence 4": "rituels",
    "Bonus 4": "+1 SEN",
    "Danger": "",
    "Magie": 1,
    "Quête": ""
  },
  {
    "Valide": 1,
    "Carrière": "Bonze",
    "Type": "Spirituel",
    "Guilde": "guilde des Ombres",
    "Filière": "maistre, vétéran",
    "Profit": 1,
    "Métier 1": "Aspirant",
    "Compétence 1": "vents magiques",
    "Bonus 1": "+1 COU",
    "Métier 2": "Moine",
    "Compétence 2": "herborisme",
    "Bonus 2": "+1 ERU",
    "Métier 3": "Pugiliste",
    "Compétence 3": "art martial",
    "Bonus 3": "+1 END",
    "Métier 4": "Bonze",
    "Compétence 4": "méditation",
    "Bonus 4": "+1 COU",
    "Danger": "",
    "Magie": 1,
    "Quête": ""
  },
  {
    "Valide": 1,
    "Carrière": "Artilleur",
    "Type": "Artisanat",
    "Guilde": "guilde des artisans",
    "Filière": "maistre, vétéran",
    "Profit": "2d6",
    "Métier 1": "Salpetrier",
    "Compétence 1": "conserves",
    "Bonus 1": "+1 END",
    "Métier 2": "Artificier",
    "Compétence 2": "explosifs",
    "Bonus 2": "+1 COU",
    "Métier 3": "Bombardier",
    "Compétence 3": "fusils",
    "Bonus 3": "+1 DEX",
    "Métier 4": "Artilleur",
    "Compétence 4": "géométrie",
    "Bonus 4": "+1 ERU",
    "Danger": 1,
    "Magie": "",
    "Quête": ""
  }
]